gbot/__init__.py
gbot/consts.py
gbot/discord.py
gbot/utils.py
gbot/apis/__init__.py
gbot/apis/github.py
gitscribe-0.1.0.data/scripts/gbot
gitscribe-0.1.0.dist-info/LICENSE
gitscribe-0.1.0.dist-info/METADATA
gitscribe-0.1.0.dist-info/WHEEL
gitscribe-0.1.0.dist-info/top_level.txt
gitscribe-0.1.0.dist-info/RECORD
